presentable_exception/__init__.py
presentable_exception/presentable_exception.py
presentable_exception/with_presentable_exception.py
django_presentable_exception-0.0.1.dist-info/LICENSE
django_presentable_exception-0.0.1.dist-info/METADATA
django_presentable_exception-0.0.1.dist-info/WHEEL
django_presentable_exception-0.0.1.dist-info/top_level.txt
django_presentable_exception-0.0.1.dist-info/RECORD
