Metadata-Version: 2.1
Name: django-presentable-exception
Version: 0.0.1
Summary: Presentable Exceptions for Django Restframework Projects
Home-page: https://github.com/tom-010/django-presentable-exception
Author: Thomas Deniffel
Author-email: tdeniffel@gmail.com
License: Apache2
Platform: UNKNOWN
Classifier: Development Status :: 4 - Beta
Classifier: Intended Audience :: Developers
Classifier: Programming Language :: Python
Classifier: Programming Language :: Python :: 3 :: Only
Classifier: Programming Language :: Python :: 3.6
Classifier: Programming Language :: Python :: 3.7
Requires-Python: >=3
License-File: LICENSE
Requires-Dist: Django (>=3.2.0)
Requires-Dist: djangorestframework (>=3.12.0)
Requires-Dist: find-class (>=0.0.1exception-safe>=0.0.3)
